CHANGES.txt
LICENSE.txt
MANIFEST.in
README.txt
setup.cfg
setup.py
js/__init__.py
js.lesscss.egg-info/PKG-INFO
js.lesscss.egg-info/SOURCES.txt
js.lesscss.egg-info/dependency_links.txt
js.lesscss.egg-info/entry_points.txt
js.lesscss.egg-info/namespace_packages.txt
js.lesscss.egg-info/not-zip-safe
js.lesscss.egg-info/requires.txt
js.lesscss.egg-info/top_level.txt
js/lesscss/__init__.py
js/lesscss/script.py
js/lesscss/test_less.txt
js/lesscss/tests.py
js/lesscss/resources/README.txt
js/lesscss/resources/less.min.js