Metadata-Version: 1.0
Name: js.lesscss
Version: 1.1.3
Summary: Fanstatic packaging of less
Home-page: UNKNOWN
Author: Stephane Klein
Author-email: stephane@harobed.org
License: BSD
Platform: UNKNOWN
